interactionfreepy/__init__.py
interactionfreepy/broker.py
interactionfreepy/core.py
interactionfreepy/worker.py
tests/__init__.py
tests/defines.py
tests/testDocExamples.py
tests/testIFWorkerAsync.py
tests/testInitBrokerAndWorker.py
tests/testInvocation.py
tests/testInvocationSerialization.py
tests/testMessageTransport.py
tests/experimental/__init__.py
tests/experimental/testRSocket.py
interactionfreepy-1.8.1.dist-info/LICENSE
interactionfreepy-1.8.1.dist-info/METADATA
interactionfreepy-1.8.1.dist-info/WHEEL
interactionfreepy-1.8.1.dist-info/top_level.txt
interactionfreepy-1.8.1.dist-info/RECORD
