Metadata-Version: 2.1
Name: interactionfreepy
Version: 1.8.1
Summary: A intuitive and cross-languige RCP lib for Python.
Home-page: https://github.com/hwaipy/InteractionFreePy
Download-URL: https://github.com/hwaipy/InteractionFreePy/archive/v1.8.1.tar.gz
Author: Hwaipy
Author-email: hwaipy@gmail.com
License: gpl-3.0
Keywords: msgpack,zeromq,zmq,0mq,rcp,cross-languige
Classifier: Development Status :: 5 - Production/Stable
Classifier: Intended Audience :: Developers
Classifier: Intended Audience :: End Users/Desktop
Classifier: License :: OSI Approved :: GNU General Public License v3 (GPLv3)
Classifier: Programming Language :: Python :: 3
Classifier: Programming Language :: Python :: 3.8
Classifier: Programming Language :: Python :: 3.9
Classifier: Programming Language :: Python :: 3.10
Classifier: Programming Language :: Python :: 3.11
Classifier: Programming Language :: Python :: 3.12
Classifier: Programming Language :: Python :: 3.13
Classifier: Programming Language :: Python :: 3.14
Requires-Python: >=3.8
License-File: LICENSE
Requires-Dist: msgpack
Requires-Dist: tornado
Requires-Dist: pyzmq
